MANIFEST.in
README
setup.py
testall.sh
Cartes/__init__.py
Cartes/ast.py
Cartes/core.py
Cartes/model.py
Cartes/parser.py
Cartes/ui.py
Cartes/images/CARREAU1.gif
Cartes/images/CARREAU10.gif
Cartes/images/CARREAU11.gif
Cartes/images/CARREAU12.gif
Cartes/images/CARREAU13.gif
Cartes/images/CARREAU2.gif
Cartes/images/CARREAU3.gif
Cartes/images/CARREAU4.gif
Cartes/images/CARREAU5.gif
Cartes/images/CARREAU6.gif
Cartes/images/CARREAU7.gif
Cartes/images/CARREAU8.gif
Cartes/images/CARREAU9.gif
Cartes/images/COEUR1.gif
Cartes/images/COEUR10.gif
Cartes/images/COEUR11.gif
Cartes/images/COEUR12.gif
Cartes/images/COEUR13.gif
Cartes/images/COEUR2.gif
Cartes/images/COEUR3.gif
Cartes/images/COEUR4.gif
Cartes/images/COEUR5.gif
Cartes/images/COEUR6.gif
Cartes/images/COEUR7.gif
Cartes/images/COEUR8.gif
Cartes/images/COEUR9.gif
Cartes/images/PIQUE1.gif
Cartes/images/PIQUE10.gif
Cartes/images/PIQUE11.gif
Cartes/images/PIQUE12.gif
Cartes/images/PIQUE13.gif
Cartes/images/PIQUE2.gif
Cartes/images/PIQUE3.gif
Cartes/images/PIQUE4.gif
Cartes/images/PIQUE5.gif
Cartes/images/PIQUE6.gif
Cartes/images/PIQUE7.gif
Cartes/images/PIQUE8.gif
Cartes/images/PIQUE9.gif
Cartes/images/TREFLE1.gif
Cartes/images/TREFLE10.gif
Cartes/images/TREFLE11.gif
Cartes/images/TREFLE12.gif
Cartes/images/TREFLE13.gif
Cartes/images/TREFLE2.gif
Cartes/images/TREFLE3.gif
Cartes/images/TREFLE4.gif
Cartes/images/TREFLE5.gif
Cartes/images/TREFLE6.gif
Cartes/images/TREFLE7.gif
Cartes/images/TREFLE8.gif
Cartes/images/TREFLE9.gif
CartesInitProg.egg-info/PKG-INFO
CartesInitProg.egg-info/SOURCES.txt
CartesInitProg.egg-info/dependency_links.txt
CartesInitProg.egg-info/requires.txt
CartesInitProg.egg-info/top_level.txt
exemples/exemple1.py
exemples/exemple2.py
exemples/exemple3.py