Metadata-Version: 1.0
Name: CartesInitProg
Version: 0.2.1
Summary: Package Cartes pour le module d'InitProg.
Home-page: http://www.fil.univ-lille1.fr/
Author: Martin Monperrus & Raphael Marvie
Author-email: {martin.monperrus,raphael.marvie}@univ-lille1.fr
License: UNKNOWN
Platform: UNKNOWN
